<?xml version="1.0" encoding="UTF-8"?>
<LanguageData>
  <!-- EN: Scrubnites Injection -->
  <MSScrubnites.label>Scrubnites Injection</MSScrubnites.label>
  <!-- EN: Scrubnites are a modified version of Antinites that specifically remove the effects of addictions. It effects last for 3 days and the pain levels associated with the treatment are somewhat reduced in comparison to Antinites. -->
  <MSScrubnites.description>Scrubnites are a modified version of Antinites that specifically remove the effects of addictions. It effects last for 3 days and the pain levels associated with the treatment are somewhat reduced in comparison to Antinites.</MSScrubnites.description>
  <!-- EN: Inject {0} -->
  <MSScrubnites.ingestible.ingestCommandString>Inject {0}</MSScrubnites.ingestible.ingestCommandString>
  <!-- EN: Injecting {0}. -->
  <MSScrubnites.ingestible.ingestReportString>Injecting {0}.</MSScrubnites.ingestible.ingestReportString>
</LanguageData>
